{
    "yesterday": {
        "A_shift.pdf": {
            "path": "yesterday/shift/A_shift.pdf",
            "last_updated": "2025-07-21 08:00:07.237547"
        },
        "B_shift.pdf": {
            "path": "yesterday/shift/B_shift.pdf",
            "last_updated": "2025-07-21 08:00:20.951159"
        },
        "C_shift.pdf": {
            "path": "yesterday/shift/C_shift.pdf",
            "last_updated": "2025-07-21 08:00:31.229560"
        },
        "OHP_report.pdf": {
            "path": "yesterday/gshift/OHP_report.pdf",
            "last_updated": "2025-07-21 08:00:38.406659"
        },
        "CHP_report.pdf": {
            "path": "yesterday/gshift/CHP_report.pdf",
            "last_updated": "2025-07-21 08:00:45.829120"
        },
        "WT_report.pdf": {
            "path": "yesterday/gshift/WT_report.pdf",
            "last_updated": "2025-07-21 08:00:55.851571"
        },
        "IOSA_report.pdf": {
            "path": "yesterday/gshift/IOSA_report.pdf",
            "last_updated": "2025-07-21 08:01:08.342685"
        }
    },
    "today": {
        "A_shift.pdf": {
            "path": "today/shift/A_shift.pdf",
            "last_updated": "2025-07-21 14:08:05.053263"
        }
    }
}