{
    "yesterday": {
        "A_shift.pdf": {
            "path": "yesterday/shift/A_shift.pdf",
            "last_updated": "2026-02-20 08:00:03.739638"
        },
        "B_shift.pdf": {
            "path": "yesterday/shift/B_shift.pdf",
            "last_updated": "2026-02-20 08:00:12.203698"
        },
        "C_shift.pdf": {
            "path": "yesterday/shift/C_shift.pdf",
            "last_updated": "2026-02-20 08:00:16.892892"
        },
        "OHP_report.pdf": {
            "path": "yesterday/gshift/OHP_report.pdf",
            "last_updated": "2026-02-20 08:00:21.436007"
        },
        "CHP_report.pdf": {
            "path": "yesterday/gshift/CHP_report.pdf",
            "last_updated": "2026-02-20 08:00:25.928313"
        },
        "WT_report.pdf": {
            "path": "yesterday/gshift/WT_report.pdf",
            "last_updated": "2026-02-20 08:00:30.214633"
        }
    },
    "today": {}
}