{
    "yesterday": {
        "A_shift.pdf": {
            "path": "yesterday/shift/A_shift.pdf",
            "last_updated": "2026-01-24 08:00:04.252469"
        },
        "B_shift.pdf": {
            "path": "yesterday/shift/B_shift.pdf",
            "last_updated": "2026-01-24 08:00:09.043915"
        },
        "C_shift.pdf": {
            "path": "yesterday/shift/C_shift.pdf",
            "last_updated": "2026-01-24 08:00:14.116983"
        },
        "CHP_report.pdf": {
            "path": "yesterday/gshift/CHP_report.pdf",
            "last_updated": "2026-01-24 07:01:07.921122"
        },
        "WT_report.pdf": {
            "path": "yesterday/gshift/WT_report.pdf",
            "last_updated": "2026-01-24 07:01:09.464707"
        },
        "OHP_report.pdf": {
            "path": "yesterday/gshift/OHP_report.pdf",
            "last_updated": "2026-01-24 08:00:24.097417"
        }
    },
    "today": {}
}