{
    "yesterday": {
        "A_shift.pdf": {
            "path": "yesterday/shift/A_shift.pdf",
            "last_updated": "2025-07-15 15:00:13.731899"
        },
        "B_shift.pdf": {
            "path": "yesterday/shift/B_shift.pdf",
            "last_updated": "2025-07-15 15:00:18.959784"
        },
        "C_shift.pdf": {
            "path": "yesterday/shift/C_shift.pdf",
            "last_updated": "2025-07-15 15:00:24.018880"
        },
        "CHP_report.pdf": {
            "path": "yesterday/gshift/CHP_report.pdf",
            "last_updated": "2025-07-15 15:00:29.208318"
        }
    },
    "today": {
        "A_shift.pdf": {
            "path": "today/shift/A_shift.pdf",
            "last_updated": "2025-07-15 15:00:08.349791"
        },
        "IOSA_report.pdf": {
            "path": "today/gshift/IOSA_report.pdf",
            "last_updated": "2025-07-15 17:30:15.581538"
        },
        "WT_report.pdf": {
            "path": "today/gshift/WT_report.pdf",
            "last_updated": "2025-07-15 17:32:30.488555"
        },
        "CHP_report.pdf": {
            "path": "today/gshift/CHP_report.pdf",
            "last_updated": "2025-07-15 17:53:24.286088"
        }
    }
}