{
    "yesterday": {
        "A_shift.pdf": {
            "path": "yesterday/shift/A_shift.pdf",
            "last_updated": "2025-06-14 08:00:06.963495"
        },
        "B_shift.pdf": {
            "path": "yesterday/shift/B_shift.pdf",
            "last_updated": "2025-06-14 08:00:14.607101"
        },
        "C_shift.pdf": {
            "path": "yesterday/shift/C_shift.pdf",
            "last_updated": "2025-06-14 08:00:21.933863"
        },
        "OHP_report.pdf": {
            "path": "yesterday/gshift/OHP_report.pdf",
            "last_updated": "2025-06-14 08:00:29.830640"
        },
        "WT_report.pdf": {
            "path": "yesterday/gshift/WT_report.pdf",
            "last_updated": "2025-06-14 08:00:44.372453"
        },
        "CHP_report.pdf": {
            "path": "yesterday/gshift/CHP_report.pdf",
            "last_updated": "2025-06-14 08:00:37.062748"
        },
        "IOSA_report.pdf": {
            "path": "yesterday/gshift/IOSA_report.pdf",
            "last_updated": "2025-06-14 08:00:54.717319"
        }
    },
    "today": {
        "A_shift.pdf": {
            "path": "today/shift/A_shift.pdf",
            "last_updated": "2025-06-14 14:48:19.914141"
        }
    }
}