{
    "yesterday": {
        "A_shift.pdf": {
            "path": "yesterday/shift/A_shift.pdf",
            "last_updated": "2025-08-07 15:00:06.327045"
        },
        "B_shift.pdf": {
            "path": "yesterday/shift/B_shift.pdf",
            "last_updated": "2025-08-07 15:00:07.998012"
        },
        "C_shift.pdf": {
            "path": "yesterday/shift/C_shift.pdf",
            "last_updated": "2025-08-07 15:00:11.107071"
        },
        "OHP_report.pdf": {
            "path": "yesterday/gshift/OHP_report.pdf",
            "last_updated": "2025-08-07 15:00:12.437188"
        },
        "CHP_report.pdf": {
            "path": "yesterday/gshift/CHP_report.pdf",
            "last_updated": "2025-08-07 15:00:13.956616"
        },
        "WT_report.pdf": {
            "path": "yesterday/gshift/WT_report.pdf",
            "last_updated": "2025-08-07 15:00:15.477864"
        }
    },
    "today": {
        "A_shift.pdf": {
            "path": "today/shift/A_shift.pdf",
            "last_updated": "2025-08-07 15:00:04.747545"
        }
    }
}