{
    "yesterday": {
        "A_shift.pdf": {
            "path": "yesterday/shift/A_shift.pdf",
            "last_updated": "2025-12-13 08:00:03.787818"
        },
        "B_shift.pdf": {
            "path": "yesterday/shift/B_shift.pdf",
            "last_updated": "2025-12-13 08:00:08.264150"
        },
        "C_shift.pdf": {
            "path": "yesterday/shift/C_shift.pdf",
            "last_updated": "2025-12-13 08:00:13.273018"
        },
        "OHP_report.pdf": {
            "path": "yesterday/gshift/OHP_report.pdf",
            "last_updated": "2025-12-13 07:01:09.133031"
        },
        "CHP_report.pdf": {
            "path": "yesterday/gshift/CHP_report.pdf",
            "last_updated": "2025-12-13 07:01:10.711137"
        },
        "WT_report.pdf": {
            "path": "yesterday/gshift/WT_report.pdf",
            "last_updated": "2025-12-13 07:01:12.451147"
        },
        "IOSA_report.pdf": {
            "path": "yesterday/gshift/IOSA_report.pdf",
            "last_updated": "2025-12-13 07:01:13.998014"
        }
    },
    "today": {}
}