{
    "yesterday": {
        "A_shift.pdf": {
            "path": "yesterday/shift/A_shift.pdf",
            "last_updated": "2025-12-11 00:15:04.999693"
        },
        "B_shift.pdf": {
            "path": "yesterday/shift/B_shift.pdf",
            "last_updated": "2025-12-11 00:15:06.922576"
        },
        "OHP_report.pdf": {
            "path": "yesterday/gshift/OHP_report.pdf",
            "last_updated": "2025-12-11 00:15:08.750700"
        },
        "CHP_report.pdf": {
            "path": "yesterday/gshift/CHP_report.pdf",
            "last_updated": "2025-12-11 00:15:10.491533"
        },
        "WT_report.pdf": {
            "path": "yesterday/gshift/WT_report.pdf",
            "last_updated": "2025-12-11 00:15:12.022772"
        },
        "IOSA_report.pdf": {
            "path": "yesterday/gshift/IOSA_report.pdf",
            "last_updated": "2025-12-11 00:15:13.570230"
        }
    },
    "today": {}
}