{
    "yesterday": {
        "A_shift.pdf": {
            "path": "yesterday/shift/A_shift.pdf",
            "last_updated": "2025-10-25 07:01:03.651489"
        },
        "B_shift.pdf": {
            "path": "yesterday/shift/B_shift.pdf",
            "last_updated": "2025-10-25 07:01:05.475245"
        },
        "C_shift.pdf": {
            "path": "yesterday/shift/C_shift.pdf",
            "last_updated": "2025-10-25 07:01:07.169065"
        },
        "OHP_report.pdf": {
            "path": "yesterday/gshift/OHP_report.pdf",
            "last_updated": "2025-10-25 07:01:08.771376"
        },
        "CHP_report.pdf": {
            "path": "yesterday/gshift/CHP_report.pdf",
            "last_updated": "2025-10-25 07:01:10.292580"
        },
        "WT_report.pdf": {
            "path": "yesterday/gshift/WT_report.pdf",
            "last_updated": "2025-10-25 07:01:11.832179"
        },
        "IOSA_report.pdf": {
            "path": "yesterday/gshift/IOSA_report.pdf",
            "last_updated": "2025-10-25 07:01:13.362830"
        }
    },
    "today": {}
}