{
    "yesterday": {
        "A_shift.pdf": {
            "path": "yesterday/shift/A_shift.pdf",
            "last_updated": "2026-05-07 00:15:04.396567"
        },
        "B_shift.pdf": {
            "path": "yesterday/shift/B_shift.pdf",
            "last_updated": "2026-05-07 00:15:04.713532"
        },
        "OHP_report.pdf": {
            "path": "yesterday/gshift/OHP_report.pdf",
            "last_updated": "2026-05-07 00:15:07.312959"
        },
        "CHP_report.pdf": {
            "path": "yesterday/gshift/CHP_report.pdf",
            "last_updated": "2026-05-07 00:15:09.761158"
        },
        "WT_report.pdf": {
            "path": "yesterday/gshift/WT_report.pdf",
            "last_updated": "2026-05-07 00:15:12.163173"
        }
    },
    "today": {}
}