{
    "yesterday": {
        "A_shift.pdf": {
            "path": "yesterday/shift/A_shift.pdf",
            "last_updated": "2025-10-23 18:30:14.250968"
        },
        "B_shift.pdf": {
            "path": "yesterday/shift/B_shift.pdf",
            "last_updated": "2025-10-23 18:30:16.120146"
        },
        "C_shift.pdf": {
            "path": "yesterday/shift/C_shift.pdf",
            "last_updated": "2025-10-23 18:30:17.808439"
        },
        "OHP_report.pdf": {
            "path": "yesterday/gshift/OHP_report.pdf",
            "last_updated": "2025-10-23 18:30:19.542276"
        },
        "CHP_report.pdf": {
            "path": "yesterday/gshift/CHP_report.pdf",
            "last_updated": "2025-10-23 18:30:21.083746"
        },
        "WT_report.pdf": {
            "path": "yesterday/gshift/WT_report.pdf",
            "last_updated": "2025-10-23 18:30:22.633583"
        },
        "IOSA_report.pdf": {
            "path": "yesterday/gshift/IOSA_report.pdf",
            "last_updated": "2025-10-23 18:30:24.172984"
        }
    },
    "today": {
        "A_shift.pdf": {
            "path": "today/shift/A_shift.pdf",
            "last_updated": "2025-10-23 18:30:05.018353"
        },
        "OHP_report.pdf": {
            "path": "today/gshift/OHP_report.pdf",
            "last_updated": "2025-10-23 18:30:07.158799"
        },
        "CHP_report.pdf": {
            "path": "today/gshift/CHP_report.pdf",
            "last_updated": "2025-10-23 18:30:09.302379"
        },
        "WT_report.pdf": {
            "path": "today/gshift/WT_report.pdf",
            "last_updated": "2025-10-23 18:30:11.043138"
        },
        "IOSA_report.pdf": {
            "path": "today/gshift/IOSA_report.pdf",
            "last_updated": "2025-10-23 18:30:12.578650"
        }
    }
}