{
    "yesterday": {
        "A_shift.pdf": {
            "path": "yesterday/shift/A_shift.pdf",
            "last_updated": "2025-07-28 23:00:34.116030"
        },
        "B_shift.pdf": {
            "path": "yesterday/shift/B_shift.pdf",
            "last_updated": "2025-07-28 23:00:39.169258"
        },
        "C_shift.pdf": {
            "path": "yesterday/shift/C_shift.pdf",
            "last_updated": "2025-07-28 23:00:44.492387"
        }
    },
    "today": {
        "A_shift.pdf": {
            "path": "today/shift/A_shift.pdf",
            "last_updated": "2025-07-28 23:00:08.445213"
        },
        "B_shift.pdf": {
            "path": "today/shift/B_shift.pdf",
            "last_updated": "2025-07-28 23:00:13.493784"
        },
        "CHP_report.pdf": {
            "path": "today/gshift/CHP_report.pdf",
            "last_updated": "2025-07-28 23:00:18.723174"
        },
        "WT_report.pdf": {
            "path": "today/gshift/WT_report.pdf",
            "last_updated": "2025-07-28 23:00:23.871349"
        },
        "IOSA_report.pdf": {
            "path": "today/gshift/IOSA_report.pdf",
            "last_updated": "2025-07-28 23:00:29.021147"
        }
    }
}