{
    "yesterday": {
        "A_shift.pdf": {
            "path": "yesterday/shift/A_shift.pdf",
            "last_updated": "2026-02-20 18:30:10.439797"
        },
        "B_shift.pdf": {
            "path": "yesterday/shift/B_shift.pdf",
            "last_updated": "2026-02-20 18:30:12.174168"
        },
        "C_shift.pdf": {
            "path": "yesterday/shift/C_shift.pdf",
            "last_updated": "2026-02-20 18:30:14.030663"
        },
        "OHP_report.pdf": {
            "path": "yesterday/gshift/OHP_report.pdf",
            "last_updated": "2026-02-20 18:30:15.788745"
        },
        "CHP_report.pdf": {
            "path": "yesterday/gshift/CHP_report.pdf",
            "last_updated": "2026-02-20 18:30:17.123659"
        },
        "WT_report.pdf": {
            "path": "yesterday/gshift/WT_report.pdf",
            "last_updated": "2026-02-20 18:30:18.664804"
        }
    },
    "today": {
        "A_shift.pdf": {
            "path": "today/shift/A_shift.pdf",
            "last_updated": "2026-02-20 18:30:05.362269"
        },
        "OHP_report.pdf": {
            "path": "today/gshift/OHP_report.pdf",
            "last_updated": "2026-02-20 18:30:07.165060"
        },
        "CHP_report.pdf": {
            "path": "today/gshift/CHP_report.pdf",
            "last_updated": "2026-02-20 18:30:08.699955"
        }
    }
}