{
    "yesterday": {
        "A_shift.pdf": {
            "path": "yesterday/shift/A_shift.pdf",
            "last_updated": "2025-05-10 18:30:28.951067"
        },
        "B_shift.pdf": {
            "path": "yesterday/shift/B_shift.pdf",
            "last_updated": "2025-05-10 18:30:34.220395"
        },
        "C_shift.pdf": {
            "path": "yesterday/shift/C_shift.pdf",
            "last_updated": "2025-05-10 18:30:39.267659"
        },
        "OHP_report.pdf": {
            "path": "yesterday/gshift/OHP_report.pdf",
            "last_updated": "2025-05-10 18:30:44.409037"
        },
        "CHP_report.pdf": {
            "path": "yesterday/gshift/CHP_report.pdf",
            "last_updated": "2025-05-10 18:30:49.534711"
        },
        "WT_report.pdf": {
            "path": "yesterday/gshift/WT_report.pdf",
            "last_updated": "2025-05-10 18:30:54.674349"
        }
    },
    "today": {
        "A_shift.pdf": {
            "path": "today/shift/A_shift.pdf",
            "last_updated": "2025-05-10 18:30:07.937936"
        },
        "OHP_report.pdf": {
            "path": "today/gshift/OHP_report.pdf",
            "last_updated": "2025-05-10 18:30:13.159044"
        },
        "CHP_report.pdf": {
            "path": "today/gshift/CHP_report.pdf",
            "last_updated": "2025-05-10 18:30:19.362664"
        },
        "IOSA_report.pdf": {
            "path": "today/gshift/IOSA_report.pdf",
            "last_updated": "2025-05-10 18:30:23.917631"
        }
    }
}